api_schemas/__init__.py
api_schemas/compilers/__init__.py
api_schemas/compilers/base.py
api_schemas/compilers/dart.py
api_schemas/compilers/python.py
api_schemas/error_handling.py
api_schemas/grammar.lark
api_schemas/intermediate_representation.py
api_schemas/parser.py
api_schemas/std_types.py
api_schemas-0.1.4.dist-info/WHEEL
api_schemas-0.1.4.dist-info/METADATA
api_schemas-0.1.4.dist-info/RECORD
