Metadata-Version: 2.1
Name: api-schemas
Version: 0.1.4
Summary: Create an intermediate representation of an api schema, that can be used to generate code.
Home-page: https://github.com/JulianSobott/api_schemas
License: MIT
Keywords: api,schema,code generation
Author: JulianSobott
Author-email: julian.sobott@gmail.com
Requires-Python: >=3.9,<4.0
Classifier: License :: OSI Approved :: MIT License
Classifier: Programming Language :: Python :: 3
Classifier: Programming Language :: Python :: 3.9
Requires-Dist: Mako (>=1.1.4,<2.0.0)
Requires-Dist: autopep8 (>=1.5.6,<2.0.0)
Requires-Dist: lark-parser (>=0.11.2,<0.12.0)
Project-URL: Repository, https://github.com/JulianSobott/api_schemas
